{
  "standings": [
    {
      "pos": 1,
      "car": "116",
      "driver": "Ashley SUTTON",
      "nat": "GBR",
      "class": "M",
      "points": 213,
      "wins": 5,
      "seconds": 4,
      "thirds": 0,
      "team": "NAPA Racing UK"
    },
    {
      "pos": 2,
      "car": "80",
      "driver": "Tom INGRAM",
      "nat": "GBR",
      "class": "M",
      "points": 156,
      "wins": 1,
      "seconds": 3,
      "thirds": 2,
      "team": "Team VERTU"
    },
    {
      "pos": 3,
      "car": "27",
      "driver": "Dan CAMMISH",
      "nat": "GBR",
      "class": "M",
      "points": 147,
      "wins": 1,
      "seconds": 1,
      "thirds": 1,
      "team": "NAPA Racing UK"
    },
    {
      "pos": 4,
      "car": "99",
      "driver": "Charles RAINFORD",
      "nat": "GBR",
      "class": "I",
      "points": 116,
      "wins": 1,
      "seconds": 0,
      "thirds": 1,
      "team": "WSR"
    },
    {
      "pos": 5,
      "car": "2",
      "driver": "Daryl DE LEON",
      "nat": "PHL",
      "class": "I",
      "points": 112,
      "wins": 0,
      "seconds": 0,
      "thirds": 2,
      "team": "WSR"
    },
    {
      "pos": 6,
      "car": "11",
      "driver": "Ricky COLLARD",
      "nat": "GBR",
      "class": "M",
      "points": 107,
      "wins": 0,
      "seconds": 2,
      "thirds": 2,
      "team": "Team VERTU"
    },
    {
      "pos": 7,
      "car": "88",
      "driver": "Mikey DOBLE",
      "nat": "GBR",
      "class": "I",
      "points": 105,
      "wins": 1,
      "seconds": 0,
      "thirds": 1,
      "team": "LKQ Euro Car Parts with Power Maxed Racing"
    },
    {
      "pos": 8,
      "car": "52",
      "driver": "Gordon SHEDDEN",
      "nat": "GBR",
      "class": "I",
      "points": 97,
      "wins": 1,
      "seconds": 0,
      "thirds": 1,
      "team": "Laser Tools Racing with MB Motorsport"
    },
    {
      "pos": 9,
      "car": "66",
      "driver": "Josh COOK",
      "nat": "GBR",
      "class": "M",
      "points": 94,
      "wins": 0,
      "seconds": 1,
      "thirds": 0,
      "team": "Speedworks Corolla Racing"
    },
    {
      "pos": 10,
      "car": "50",
      "driver": "\u00c1r\u00f3n TAYLOR-SMITH",
      "nat": "IRL",
      "class": "I",
      "points": 80,
      "wins": 1,
      "seconds": 0,
      "thirds": 0,
      "team": "Laser Tools Racing with MB Motorsport"
    },
    {
      "pos": 11,
      "car": "3",
      "driver": "Tom CHILTON",
      "nat": "GBR",
      "class": "M",
      "points": 79,
      "wins": 0,
      "seconds": 0,
      "thirds": 1,
      "team": "Team VERTU"
    },
    {
      "pos": 12,
      "car": "33",
      "driver": "Adam MORGAN",
      "nat": "GBR",
      "class": "M",
      "points": 78,
      "wins": 0,
      "seconds": 0,
      "thirds": 0,
      "team": "Cataclean Plato Racing"
    },
    {
      "pos": 13,
      "car": "16",
      "driver": "Aiden MOFFAT",
      "nat": "GBR",
      "class": "I",
      "points": 75,
      "wins": 0,
      "seconds": 0,
      "thirds": 0,
      "team": "LKQ Euro Car Parts with Power Maxed Racing"
    },
    {
      "pos": 14,
      "car": "17",
      "driver": "Dexter PATTERSON",
      "nat": "GBR",
      "class": "I",
      "points": 67,
      "wins": 0,
      "seconds": 0,
      "thirds": 0,
      "team": "Steel Seal with Power Maxed Racing"
    },
    {
      "pos": 15,
      "car": "22",
      "driver": "Chris SMILEY",
      "nat": "GBR",
      "class": "I",
      "points": 64,
      "wins": 0,
      "seconds": 0,
      "thirds": 0,
      "team": "Restart Racing"
    },
    {
      "pos": 16,
      "car": "32",
      "driver": "Daniel ROWBOTTOM",
      "nat": "GBR",
      "class": "M",
      "points": 61,
      "wins": 0,
      "seconds": 0,
      "thirds": 0,
      "team": "Cataclean Plato Racing"
    },
    {
      "pos": 17,
      "car": "77",
      "driver": "Sam OSBORNE",
      "nat": "GBR",
      "class": "M",
      "points": 39,
      "wins": 0,
      "seconds": 0,
      "thirds": 0,
      "team": "NAPA Racing UK"
    },
    {
      "pos": 18,
      "car": "132",
      "driver": "James DORLIN",
      "nat": "GBR",
      "class": "I",
      "points": 32,
      "wins": 0,
      "seconds": 0,
      "thirds": 0,
      "team": "Restart Racing"
    },
    {
      "pos": 19,
      "car": "15",
      "driver": "Lewis SELBY",
      "nat": "GBR",
      "class": "M",
      "points": 17,
      "wins": 0,
      "seconds": 0,
      "thirds": 0,
      "team": "NAPA Racing UK"
    },
    {
      "pos": 20,
      "car": "28",
      "driver": "Nicolas HAMILTON",
      "nat": "GBR",
      "class": "M",
      "points": 6,
      "wins": 0,
      "seconds": 0,
      "thirds": 0,
      "team": "Team VERTU"
    },
    {
      "pos": 21,
      "car": "19",
      "driver": "Max BUXTON",
      "nat": "GBR",
      "class": "M",
      "points": 0,
      "wins": 0,
      "seconds": 0,
      "thirds": 0,
      "team": "Speedworks Corolla Racing"
    }
  ],
  "teams": [
    {
      "pos": 1,
      "team": "NAPA Racing UK",
      "points": 311
    },
    {
      "pos": 2,
      "team": "WSR",
      "points": 204
    },
    {
      "pos": 3,
      "team": "Team VERTU",
      "points": 199
    },
    {
      "pos": 4,
      "team": "LKQ Euro Car Parts with Power Maxed Racing",
      "points": 173
    },
    {
      "pos": 5,
      "team": "Laser Tools Racing with MB Motorsport",
      "points": 168
    },
    {
      "pos": 6,
      "team": "Cataclean Plato Racing",
      "points": 121
    },
    {
      "pos": 7,
      "team": "Restart Racing",
      "points": 114
    },
    {
      "pos": 8,
      "team": "Speedworks Corolla Racing",
      "points": 87
    },
    {
      "pos": 9,
      "team": "Steel Seal with Power Maxed Racing",
      "points": 60
    }
  ],
  "manufacturers": [
    {
      "pos": 1,
      "points": 359,
      "manufacturer": "Alliance Racing / Ford"
    },
    {
      "pos": 2,
      "points": 249,
      "manufacturer": "EXCELR8 Motorsport / Hyundai"
    },
    {
      "pos": 3,
      "points": 224,
      "manufacturer": "Mercedes"
    },
    {
      "pos": 4,
      "points": 191,
      "manufacturer": "Toyota"
    }
  ],
  "independentsTeams": [
    {
      "pos": 1,
      "team": "LKQ Euro Car Parts with Power Maxed Racing",
      "points": 187
    },
    {
      "pos": 2,
      "team": "Laser Tools Racing with MB Motorsport",
      "points": 184
    },
    {
      "pos": 3,
      "team": "WSR",
      "points": 179
    },
    {
      "pos": 4,
      "team": "Restart Racing",
      "points": 153
    },
    {
      "pos": 5,
      "team": "Steel Seal with Power Maxed Racing",
      "points": 122
    }
  ],
  "jst": [
    {
      "pos": 1,
      "car": "17",
      "driver": "Dexter PATTERSON",
      "nat": "GBR",
      "class": "I",
      "points": 175,
      "wins": 5,
      "seconds": 2,
      "thirds": 2,
      "team": "Steel Seal with Power Maxed Racing"
    },
    {
      "pos": 2,
      "car": "132",
      "driver": "James DORLIN",
      "nat": "GBR",
      "class": "I",
      "points": 175,
      "wins": 3,
      "seconds": 2,
      "thirds": 3,
      "team": "Restart Racing"
    },
    {
      "pos": 3,
      "car": "77",
      "driver": "Sam OSBORNE",
      "nat": "GBR",
      "class": "M",
      "points": 151,
      "wins": 2,
      "seconds": 3,
      "thirds": 4,
      "team": "NAPA Racing UK"
    },
    {
      "pos": 4,
      "car": "15",
      "driver": "Lewis SELBY",
      "nat": "GBR",
      "class": "M",
      "points": 129,
      "wins": 1,
      "seconds": 2,
      "thirds": 1,
      "team": "NAPA Racing UK"
    },
    {
      "pos": 5,
      "car": "28",
      "driver": "Nicolas HAMILTON",
      "nat": "GBR",
      "class": "M",
      "points": 115,
      "wins": 0,
      "seconds": 2,
      "thirds": 1,
      "team": "Team VERTU"
    },
    {
      "pos": 6,
      "car": "19",
      "driver": "Max BUXTON",
      "nat": "GBR",
      "class": "M",
      "points": 95,
      "wins": 0,
      "seconds": 0,
      "thirds": 0,
      "team": "Speedworks Corolla Racing"
    }
  ],
  "season": "2026",
  "round": 4,
  "venue": "Oulton Park",
  "updated": "2026-06-07T16:06:25Z"
}